[
{"name": "太极 腰痛丸", "company": "太极集团浙江东方制药有限公司", "function": "​补肾活血，强筋止痛。用于肾阳不足、瘀血阻络所致的腰痛及腰肌劳损。"},
{"name": "君碧莎 桂芍镇痫片", "company": "陕西君碧莎制药有限公司", "function": "调和营卫，清肝胆。用于治疗各种发作类型的癫痫。"},
{"name": "恩威 洁尔阴洗液", "company": "四川恩威制药有限公司", "function": "清热燥湿，杀虫止痒。"},
{"name": "良方制药 润伊容胶囊", "company": "云南良方制药有限公司", "function": "傣医：别菲解逼。兵休占，兵那干。"},
{"name": "气血和 气血和胶囊", "company": "陕西摩美得气血和制药有限公司", "function": "疏肝理气，活血止痛。用于妇女月经过少，经期后错，行经不畅，经色黯红有血块，小腹或少腹疼痛，乳房胀痛，或伴有黄褐色斑等面部色素沉着。"},
{"name": "莎普爱思", "company": "浙江莎普爱思药业股份有限公司", "function": "早期老年性白内障。"},
{"name": "喀什昆仑维吾尔 复方驱虫斑鸠菊丸", "company": "喀什昆仑维吾尔药业股份有限公司", "function": "本品熟化和清除异常粘液质，温肤着色。祛风生津，祛风驱湿，促进黑色素小细胞生成。用于白癜风、银屑病。"},
{"name": "新天夫 益肾壮阳膏", "company": "海南新天夫药业有限公司", "function": "补肾壮阳、活血通络。用于阴茎勃起功能障碍，中医辨证属肾阳虚者。"},
{"name": "太极 生力雄丸", "company": "太极集团重庆桐君阁药厂有限公司", "function": "补肾壮阳，益髓填精。用于肾精亏损，性欲减退，阳痿早泄，夜尿频多，腰膝酸软，畏寒肢冷，白发脱发等症。"},
{"name": "康王 复方酮康唑发用洗剂", "company": "滇虹药业集团股份有限公司", "function": "用于治疗和预防多种真菌引起的感染，如头皮糠疹（头皮屑）、脂溢性皮炎和花斑癣。能迅速缓解由脂溢性皮炎和头皮糠疹引起的脱屑和瘙痒。"},
{"name": "马应龙 马应龙麝香痔疮膏", "company": "马应龙药业集团股份有限公司", "function": "清热燥湿，活血消肿，去腐生肌。用于湿热瘀阻所致的痔疮、肛裂，症见大便出血，或疼痛、有下坠感；亦用于肛周湿疹。"},
{"name": "鑫字牌 妇炎康片", "company": "广东德鑫制药有限公司", "function": "清热利湿，理气活血，散结消肿。用于湿热下注、毒瘀互阻所致带下病，症见带下量多、色黄、气臭，少腹痛，腰骶痛，口苦咽干；阴道炎、慢性盆腔炎见上述证候者。"},
{"name": "奇正 消痛贴膏", "company": "西藏奇正藏药股份有限公司", "function": "活血化瘀，消肿止痛。用于急慢性扭挫伤、跌打瘀痛、骨质增生、风湿及类风湿疼痛。亦适用于落枕、肩周炎、腰肌劳损和陈旧性伤痛等。"},
{"name": "云南白药 云南白药膏", "company": "云南白药集团无锡药业有限公司", "function": "活血散瘀，消肿止痛，祛风除湿。用于跌打损伤，瘀血肿痛，风湿疼痛等症。"},
{"name": "太平 曲安奈德益康唑乳膏", "company": "福建太平洋制药有限公司", "function": "适用于足癣,体癣,股癣,花班癣和湿疹。"},
{"name": "祺笑 化瘀祛斑胶囊", "company": "山西仁源堂药业有限公司", "function": "疏风清热，活血化瘀。用于黄褐斑、酒渣、粉刺。"},
{"name": "宝宝一贴灵 丁桂儿脐贴", "company": "亚宝药业集团股份有限公司", "function": "健脾温中，散寒止泻。适用于小儿泄泻，腹痛的辅助治疗。"},
{"name": "龙牡 龙牡壮骨颗粒", "company": "健民药业集团股份有限公司", "function": "强筋壮骨，和胃健脾。用于治疗和预防小儿佝偻病，软骨病；对小儿多汗、夜惊、食欲不振、消化不良、发育迟缓也有治疗作用。"},
{"name": "源安堂 复方黄松洗液", "company": "广西源安堂药业有限公司", "function": "清热燥湿，祛风止痒。用于湿热下注所致的阴部瘙痒，或灼热痛，带下量多，色黄；霉菌性、滴虫性阴道炎及外阴炎。"},
{"name": "妈咪爱", "company": "北京韩美药品有限公司", "function": "适用于因肠道菌群失调引起的腹泻、便秘、胀气、消化不良等。"}
]